image_app/SmoothAreaProvider.py
image_app/__init__.py
image_app/area.py
image_app/libs/__init__.py
image_app/libs/select_by_kp.cpython-36m-x86_64-linux-gnu.so
image_app/libs/select_by_kp.cpython-37m-darwin.so
image_app-0.0.3.20041619.dist-info/LICENSE
image_app-0.0.3.20041619.dist-info/METADATA
image_app-0.0.3.20041619.dist-info/WHEEL
image_app-0.0.3.20041619.dist-info/top_level.txt
image_app-0.0.3.20041619.dist-info/RECORD
