Metadata-Version: 2.1
Name: image-app
Version: 0.0.3.20041619
Summary: 图片处理
Home-page: https://github.com/BingerYang/image_app
Author: binger
Author-email: <xuehen_521@126.com>
Maintainer: binger
Maintainer-email: <xuehen_521@126.com>
License: MITT
Platform: all
Requires-Python: >=3.4
